[
    {
        "text": "Pilze sammeln",
        "column": "two"
    },
    {
        "text": "Steinschlag",
        "column": "one"
    },
    {
        "text": "Reiten",
        "column": "three"
    },
    {
        "text": "Wandern",
        "column": "three"
    },
    {
        "text": "Christbaum schlagen",
        "column": "two"
    },
    {
        "text": "Joggen",
        "column": "three"
    },
    {
        "text": "Jagd",
        "column": "two"
    },
        {
        "text": "Hochwasser",
        "column": "one"
    },
    {
        "text": "Mountainbike fahren",
        "column": "three"
    },
    {
        "text": "Brennholz",
        "column": "two"
    },
    {
        "text": "Papier herstellen",
        "column": "two"
    },
    {
        "text": "Möbel",
        "column": "two"
    },
    {
        "text": "Erdrutsch",
        "column": "one"
    },
    {
        "text": "Artenvielfalt erhalten",
        "column": "four"
    },
    {
        "text": "Naturschutzgebiete ausweisen",
        "column": "four"
    },
    {
        "text": "Lärm",
        "column": "one"
    },
    {
        "text": "Artenschutz",
        "column": "four"
    },
    {
        "text": "Lawinen",
        "column": "one"
    },
    {
        "text": "Biotope schützen",
        "column": "four"
    },
    {
        "text": "Regenwasser filtern",
        "column": "two"
    }

]
